{
  "type": "origins:multiple",
  "more_infire_damage": {
    "type": "origins:modify_damage_taken",
    "damage_condition": {
      "type": "origins:name",
      "name": "inFire"
    },
    "modifier": {
      "operation": "multiply_total",
      "id": "origins-plus-plus:737bd220_8fae_45d2_befb_6fc2ccace782",
      "amount": 2
    }
  },
  "more_onfire_damage": {
    "type": "origins:modify_damage_taken",
    "damage_condition": {
      "type": "origins:name",
      "name": "onFire"
    },
    "modifier": {
      "operation": "add_multiplied_total",
      "id": "origins-plus-plus:d768d526_b514_4095_a672_ff90cc10628e",
      "amount": 2
    }
  },
  "more_lighting_damage": {
    "type": "origins:modify_damage_taken",
    "damage_condition": {
      "type": "origins:name",
      "name": "lightningBolt"
    },
    "modifier": {
      "operation": "add_multiplied_total",
      "id": "origins-plus-plus:66006b93_44af_429c_ae84_e45623084f4e",
      "amount": 1
    }
  },
  "more_lava_damage": {
    "type": "origins:modify_damage_taken",
    "damage_condition": {
      "type": "origins:name",
      "name": "lava"
    },
    "modifier": {
      "operation": "add_multiplied_total",
      "id": "origins-plus-plus:57e021f1_e88c_4dd1_81e9_6aba5d69b52d",
      "amount": 5
    }
  },
  "more_firework_damage": {
    "type": "origins:modify_damage_taken",
    "damage_condition": {
      "type": "origins:name",
      "name": "fireworks"
    },
    "modifier": {
      "operation": "add_multiplied_total",
      "id": "origins-plus-plus:c73dabe8_54cd_4870_8918_09df37c939f7",
      "amount": 2
    }
  }
}